LICENSE
README.md
setup.cfg
setup.py
compass/__init__.py
compass/agents_base.py
compass/allocator.py
compass/functions.py
compass/household.py
compass/model.py
compass/neighbourhood.py
compass/parameters.py
compass/scheduler.py
compass/school.py
compass/student.py
compass/utils.py
compass/visualisation.py
compass_school.egg-info/PKG-INFO
compass_school.egg-info/SOURCES.txt
compass_school.egg-info/dependency_links.txt
compass_school.egg-info/requires.txt
compass_school.egg-info/top_level.txt