Metadata-Version: 2.1
Name: compass-school
Version: 1.1.0
Summary: This Python implementation tries to model school choice and resulting school segregation based on the work of Schelling (1971) and Stoica & Flache (2014).
Home-page: https://github.com/ODISSEI-School-Choice/school-choice
Download-URL: https://github.com/ODISSEI-School-Choice/school-choice/archive/refs/tags/v1.0.0.tar.gz
Author: Eric Digum, Jisk Attenma, Ji Qi
Author-email: e.p.n.dignum@uva.nl, j.attema@esciencecenter.nl, j.qi@esciencecenter.nl
Requires-Python: >=3.10
License-File: LICENSE
